{
  "recipes": [
    {
      "id": 1,
      "name": "Apple Frangipan Tart",
      "image": "https://www.themealdb.com/images/media/meals/wxywrq1468235067.jpg"
    },
    {
      "id": 2,
      "name": "Apple Frangipan Tart",
      "image": "https://www.themealdb.com/images/media/meals/wxywrq1468235067.jpg"
    },
    {
      "id": 3,
      "name": "Apple Frangipan Tart",
      "image": "https://www.themealdb.com/images/media/meals/wxywrq1468235067.jpg"
    },
    {
      "id": 4,
      "name": "Apple Frangipan Tart",
      "image": "https://www.themealdb.com/images/media/meals/wxywrq1468235067.jpg"
    },
    {
      "name": "123",
      "image": "222",
      "id": 5
    }
  ]
}